sogou_search/__init__.py
sogou_search/sogou_search.py
k_sogou_search-0.0.2.dist-info/METADATA
k_sogou_search-0.0.2.dist-info/WHEEL
k_sogou_search-0.0.2.dist-info/top_level.txt
k_sogou_search-0.0.2.dist-info/RECORD
