Metadata-Version: 2.4
Name: k-sogou-search
Version: 0.0.2
Summary: A simple unofficial API to get search results from Sogou.
Home-page: https://github.com/li-xiu-qi/sogou_search
Author: li-xiu-qi
Author-email: lixiuqixiaoke@qq.com
Classifier: Programming Language :: Python :: 3
Classifier: License :: OSI Approved :: MIT License
Classifier: Operating System :: OS Independent
Requires-Python: >=3.6
Requires-Dist: requests
Requires-Dist: beautifulsoup4
Dynamic: author
Dynamic: author-email
Dynamic: classifier
Dynamic: description
Dynamic: description-content-type
Dynamic: home-page
Dynamic: requires-dist
Dynamic: requires-python
Dynamic: summary
